robotframework_historic_listener/Listener.py
robotframework_historic_listener/__init__.py
robotframework_historic_listener-0.1.8.dist-info/LICENSE
robotframework_historic_listener-0.1.8.dist-info/METADATA
robotframework_historic_listener-0.1.8.dist-info/WHEEL
robotframework_historic_listener-0.1.8.dist-info/top_level.txt
robotframework_historic_listener-0.1.8.dist-info/RECORD
